{
    "office": "Minister for Communications (Australia)",
    "term_start": "26 May 2019",
    "primeminister": "Scott Morrison",
    "predecessor": "Mitch Fifield",
    "office1": "Minister for Families and Social Services",
    "primeminister1": "Scott Morrison",
    "term_start1": "28 August 2018",
    "predecessor1": "Dan Tehan",
    "successor1": "Anne Ruston",
    "office2": "Minister for Infrastructure and Regional Development (Australia)#List of ministers for urban development and cities",
    "primeminister2": "Malcolm Turnbull, Scott Morrison",
    "term_start2": "19 July 2016",
    "term_end2": "27 August 2018",
    "predecessor2": "Jamie Briggs",
    "successor2": "Alan Tudge",
    "office3": "Minister for Infrastructure and Regional Development (Australia)#List of ministers for regional development, territories and local government",
    "primeminister3": "Malcolm Turnbull",
    "term3": "21 September 2015 \u2013 16 July 2017 27 October 2017 \u2013 20 December 2017",
    "predecessor3": "Fiona Nash",
    "successor3": "John McVeigh (politician)",
    "constituency_MP4": "Division of Bradfield",
    "parliament4": "Australian",
    "term_start4": "5 December 2009",
    "predecessor4": "Brendan Nelson",
    "birth_name": "Paul William Fletcher",
    "citizenship": [],
    "party": "Liberal Party of Australia",
    "spouse": "Manuela Zappacosta",
    "children": "2",
    "alma_mater": [],
    "DATE_TIME": "2019-05-26T13:02:01Z"
}