{
    "name": "Alberto Fujimori",
    "office": "45th, 46th & 47th President of the Republic of Peru",
    "term_start": "28 July 1990",
    "term_end": "22 November 2000",
    "vicepresident": "Francisco Tudela (1st), Ricardo M\u00e1rquez (2nd)",
    "primeminister": "Federico Salas",
    "term_start2": "28 July 1995",
    "term_end2": "28 July 2000",
    "predecessor2": "Himself (President of the Government of Emergency and National Reconstruction)",
    "successor2": "Himself",
    "vicepresident2": "Ricardo M\u00e1rquez (1st), C\u00e9sar Paredes (2nd)",
    "primeminister2": "Dante Cordova, Alberto Pandolfi, Javier Valle Riestra, Alberto Pandolfi, V\u00edctor Joy Way, Alberto Bustamante Belaunde",
    "term_start3": "28 July 1990",
    "term_end3": "5 April 1992",
    "predecessor3": "Alan Garc\u00eda",
    "successor3": "Himself (President of the Government of Emergency and National Reconstruction)",
    "vicepresident3": "M\u00e1ximo San Rom\u00e1n (1st), Carlos Garc\u00eda Garc\u00eda (2nd)",
    "primeminister3": "Juan Carlos Hurtado Miller, Carlos Torres y Torres Lara, Alfonso de los Heros",
    "office4": "President of the Government of Emergency and National Reconstruction of Peru",
    "term_start4": "5 April 1992",
    "term_end4": "28 July 1995",
    "predecessor4": "Himself",
    "successor4": "Himself",
    "vicepresident4": "None",
    "primeminister4": "\u00d3scar de la Puente, Alfonso Bustamante y Belaunde, Efrain Goldenberg",
    "spouse": "Susana Higuchi (1974-1994), Satomi Kataoka",
    "alma_mater": "Universidad Nacional Agraria La Molina University of Strasbourg University of Wisconsin\u2013Milwaukee",
    "religion": "Roman Catholicism",
    "otherparty": "Cambio 90 (1990\u20131999), Peru 2000 (2000), Alliance for the Future (2006) ",
    "DATE_TIME": "2013-02-23T15:33:22Z"
}