{
    "name": "Melbourne Renegades",
    "captain": "Aaron Finch",
    "coach": "David Saker",
    "chairman": "Jason Dunstall",
    "battingcoach": "Lloyd Mash",
    "bowlingcoach": "Tim McCaskill",
    "fieldingcoach": "Neil Buszard",
    "colours": "color box",
    "founded": "2011",
    "ground": "Docklands Stadium",
    "capacity": "56,347",
    "ceo": "Stuart Coventry",
    "fcdebutvs": "Adelaide Strikers",
    "fcdebutyr": "2011",
    "fcdebutvenue": "Adelaide Oval",
    "no": "0",
    "current": "Current season ",
    "DATE_TIME": "2016-01-05T10:10:02Z"
}