{
    "office": "Speaker of the House of Commons |honorific-prefix = The Right Honourable |honorific-suffix = ",
    "monarch": "Elizabeth II",
    "leader2": "Iain Duncan Smith",
    "office2": "Shadow Chief Secretary to the Treasury",
    "predecessor2": "Oliver Letwin",
    "successor2": "Howard Flight",
    "party": "None ",
    "leader1": "Michael Howard",
    "office1": "Shadow Secretary of State for International Development",
    "predecessor1": "Caroline Spelman",
    "successor1": "Alan Duncan",
    "children": "3",
    "alma_mater": "University of Essex",
    "term_start": "22 June 2009",
    "term_start1": "10 November 2003",
    "term_end1": "8 September 2004",
    "term_start2": "18 September 2001",
    "term_end2": "23 July 2002",
    "office3": "Member of Parliament, for Buckingham",
    "term_start3": "1 May 1997",
    "predecessor3": "George Walden",
    "majority3": "22,942 (42.7%)",
    "DATE_TIME": "2017-02-07T01:41:43Z"
}