{
    "name": "University of Chicago",
    "endowment": "$7.550 billion (2015)",
    "president": "Robert J. Zimmer",
    "provost": "Daniel Diermeier",
    "students": "15,726",
    "undergrad": "5,860",
    "postgrad": "9,866",
    "campus": "Urban  ",
    "athletics": "NCAA Division III \u2013 UAA",
    "affiliations": "AAU, NAICU, URA",
    "image_name": "https://upload.wikimedia.org/wikipedia/en/thumb/8/8a/University_of_Chicago_Modern_Etched_Seal_1.svg/-University_of_Chicago_Modern_Etched_Seal_1.svg.png",
    "faculty": "2,274",
    "staff": "14,772 (including employees of the University of Chicago Medical Center)",
    "DATE_TIME": "2016-10-16T18:31:32Z"
}