{
    "common_name": "Eastern Ganga Empire",
    "life_span": [
        "505\u20131038 CE (Kalinga)",
        "1038\u20131434 CE (Trikalinga)"
    ],
    "width": "280 | imag",
    "religion": "Hinduism",
    "leader1": "Kamarnava Deva II",
    "year_leader1": "1015-1038",
    "leader2": "Vajrahasta Anantavarman",
    "year_leader2": "1038\u20131070",
    "leader3": "Rajaraja Devendravarman",
    "year_leader3": "1070\u20131078",
    "leader4": "Anantavarman Chodagangadeva",
    "year_leader4": "1077\u20131150",
    "leader5": "Ananga Bhima Deva II",
    "year_leader5": "1178\u20131198",
    "leader6": "Anangabhima Deva III",
    "year_leader6": "1211\u20131238",
    "leader7": "Narasingha Deva I",
    "year_leader7": "1238\u20131264",
    "leader8": "Bhanu Deva IV",
    "year_leader8": "1414\u20131434",
    "title_leader": "Tri-Kalingadhipati Gajapati",
    "DATE_TIME": "2022-12-07T19:57:02Z"
}