{
    "common_name": "Vatican City",
    "largest_city": "capital",
    "official_languages": "Italian",
    "leader_title1": "Sovereign entity",
    "leader_name1": "Holy See",
    "leader_title2": "Sovereign",
    "leader_title3": "Secretary of State",
    "leader_name3": "Pietro Parolin",
    "leader_title4": "President of the Governorate",
    "leader_name4": "Giuseppe Bertello",
    "sovereignty_type": "Independence ",
    "area_km2": "0.49",
    "area_rank": "194th",
    "population_estimate": "825name=population",
    "population_estimate_year": "2019",
    "population_estimate_rank": "240th",
    "population_density_km2": "924",
    "population_density_rank": "12th",
    "religion": "Catholicism",
    "DATE_TIME": "2020-06-25T21:26:14Z"
}