{
    "clubname": "Olympiacos",
    "ground": "Karaiskakis Stadium",
    "capacity": "32,115<ref name",
    "current": "2018\u201319 Olympiacos F.C. season",
    "owner": "Evangelos Marinakis",
    "chrtitle": "President",
    "chairman": "Yannis Moralis (politician)",
    "manager": "Pedro Martins (footballer)",
    "mgrtitle": "Head coach",
    "league": "Superleague Greece",
    "position": "Super League, 3rd",
    "season": "2017\u201318 Superleague Greece",
    "DATE_TIME": "2019-02-10T19:34:24Z"
}