{
    "clubname": "Newport County AFC",
    "ground": "Rodney Parade",
    "capacity": "7,850",
    "coordinates": "coord",
    "owner": "Newport County AFC Supporters Trust",
    "chairman": "Gavin Foxall",
    "manager": "Darren Kelly (caretaker)",
    "league": "English football updater",
    "season": "English football updater",
    "position": "English football updater",
    "current": "2022\u201323 Newport County A.F.C. season   '''Newport County Association Football Club''' (lang-cy",
    "publisher": "BBC Sport",
    "date": "yes (founded), Start",
    "rowspan": "5 | None |- |1975\u20131976 | None |- |1976\u20131977 | Bukta |- |1977\u20131979 | Adidas |- |1982\u20131983 |",
    "DATE_TIME": "2022-10-12T21:13:02Z"
}