{
    "name": "Germany",
    "association": "German Cricket Federation",
    "captain": "Venkatraman Ganesan",
    "coach": "Atiq-uz-Zaman",
    "icc_status2": "Associate",
    "icc_member_year2": "1999",
    "t20i_rank": "33rd",
    "t20i_rank_best": "30th  (26 June 2019)",
    "first_match": "v. cr",
    "most_recent_t20i": "v. cr",
    "num_t20is": "46",
    "num_t20is_this_year": "6",
    "t20i_record": "30/16 (0 ties, 0 no results)",
    "t20i_record_this_year": "6/0 (0 ties, 0 no results)",
    "asofdate": "30 June 2023 ",
    "DATE_TIME": "2023-06-30T10:19:19Z"
}