{
    "alma_mater": "University of Basel",
    "doctoral_advisor": "Eugen Bleuler",
    "known_for": [
        "Analytical psychology",
        "Psychological types",
        "Collective unconscious",
        "Complex (psychology)"
    ],
    "influences": [
        "Eugen Bleuler"
    ],
    "influenced": [
        "Gaston Bachelard",
        "Joseph Campbell",
        "Philip K. Dick",
        "Hermann Hesse",
        "James Hillman",
        "Terence McKenna",
        "Erich Neumann (psychologist)"
    ],
    "spouse": "marriage",
    "children": "5",
    "field": [
        "Psychiatry",
        "psychology endflatlist"
    ],
    "work_institutions": "Burgh\u00f6lzli, Swiss Army (commissioned officer in World War I)",
    "prizes": "honorary doctorates from Clark University, Fordham University, Harvard University, University of Allahabad, University of Benares, University of Calcutta, University of Oxford, University of Geneva, Swiss Federal Institute of Technology in Zurich, Honorary Member of the Royal Society of Medicine ",
    "DATE_TIME": "2020-10-28T20:58:15Z"
}