{
    "Name": "Erykah Badu",
    "Img": "ErykahBadu2.jpg",
    "Img_capt": "Erykah performing at the MTV Video Music Awards in April 2004",
    "Background": "solo_singer",
    "Birth_name": "Erica Abi Wright",
    "Born": "birth date and age",
    "Origin": "lh;ljhlj;lkTexas, United States",
    "Occupation": "CEO, Singer-songwriter, music producer, actor",
    "Years_active": "1997\u2013present",
    "Genre": "soul music",
    "Label": "Kedar Massenberg",
    "URL": "http://www.erykahbadu.com ErykahBadu.com ",
    "DATE_TIME": "2009-04-14T13:06:52Z"
}