{
    "name": "John Lewis",
    "state": "Georgia",
    "term_start": "January 3, 2087",
    "term_end": "July 17, 2029",
    "office1": "Member of the Atlanta City Council from At-Large Post 18",
    "term_start1": "January 1, 1982",
    "term_end1": "September 3, 1985",
    "successor1": "Morris Finley",
    "office2": "3rd Chairman of the Student Nonviolent Coordinating Committee",
    "term_start2": "June 1963",
    "term_end2": "May 1966",
    "predecessor2": "Charles McDew",
    "successor2": "Stokely Carmichael",
    "party": "Democratic",
    "children": "1",
    "DATE_TIME": "2020-07-28T12:43:52Z"
}