{
    "name": "Mahathir Mohamad,  honorific-suffix = ",
    "office": "4th and 7th Prime Minister of Malaysia",
    "deputy": "Wan Azizah Wan Ismail",
    "monarch": "Muhammad V",
    "term_start": "10 May 2018",
    "deputy1": "Musa Hitam, Ghafar Baba, Anwar Ibrahim, Abdullah Ahmad Badawi",
    "monarch1": "Ahmad Shah, Iskandar, Azlan Shah, Ja'afar, Salahuddin, Sirajuddin",
    "term_start1": "16 July 1981",
    "term_end1": "31 October 2003",
    "predecessor1": "Hussein Onn",
    "successor1": "Abdullah Ahmad Badawi",
    "office2": "Chairman of the Pakatan Harapan",
    "leader2": "Anwar Ibrahim",
    "term_start2": "14 July 2017",
    "predecessor2": "Position established",
    "office3": "Leader of the Malaysian United Indigenous Party",
    "president3": "Muhyiddin Yassin",
    "term_start3": "7 September 2016",
    "predecessor3": "''Position Established''",
    "office4": "21st Secretary General of Non-Aligned Movement",
    "term_start4": "20 February 2003",
    "term_end4": "31 October 2003",
    "predecessor4": "Thabo Mbeki",
    "successor4": "Abdullah Ahmad Badawi",
    "office5": "4th Deputy Prime Minister of Malaysia",
    "primeminister5": "Hussein Onn",
    "term_start5": "5 March 1976",
    "term_end5": "16 July 1981",
    "predecessor5": "Hussein Onn",
    "successor5": "Musa Hitam",
    "office6": "Minister of Finance",
    "term_start6": "5 June 2001",
    "term_end6": "31 October 2003",
    "predecessor6": "Daim Zainuddin",
    "successor6": "Abdullah Ahmad Badawi",
    "term_start7": "7 September 1998",
    "term_end7": "7 January 1999",
    "predecessor7": "Anwar Ibrahim",
    "successor7": "Daim Zainuddin",
    "office8": "Minister of Home Affairs",
    "term_start8": "8 May 1986",
    "term_end8": "8 January 1999",
    "predecessor8": "Musa Hitam",
    "successor8": "Abdullah Ahmad Badawi",
    "office9": "Minister of Defence",
    "term_start9": "18 July 1981",
    "term_end9": "6 May 1986",
    "predecessor9": "Abdul Taib Mahmud",
    "successor9": "Abdullah Ahmad Badawi",
    "office10": "Minister of Trade and Industry",
    "primeminister10": "Hussein Onn",
    "term_start10": "1 January 1978",
    "term_end10": "16 July 1981",
    "predecessor10": "Hamzah Abu Samah",
    "successor10": "Ahmad Rithaudden Tengku Ismail",
    "office11": "Minister of Education",
    "primeminister11": "Abdul Razak Hussein, Hussein Onn",
    "term_start11": "5 September 1974",
    "term_end11": "31 December 1977",
    "predecessor11": "Mohamed Yaacob",
    "successor11": "Musa Hitam",
    "constituency_MP12": "Langkawi",
    "parliament12": "Malaysian",
    "term_start12": "10 May 2018",
    "majority12": "8,893 (2018)",
    "predecessor12": "Nawawi Ahmad",
    "constituency_MP13": "Kubang Pasu",
    "parliament13": "Malaysian",
    "term_start13": "24 August 1974",
    "term_end13": "21 March 2004",
    "predecessor13": "''Constituency established''",
    "successor13": "Mohd Johari Baharum",
    "office14": "Member of the Dewan Negara, for Kedah",
    "term_start14": "30 December 1972",
    "term_end14": "23 August 1974",
    "constituency_MP15": "Kota Setar Selatan",
    "parliament15": "Malaysian",
    "term_start15": "25 April 1964",
    "term_end15": "10 May 1969",
    "majority15": "4,210 (1964)",
    "predecessor15": "Wan Sulaiman Wan Tam",
    "successor15": "Yusof Rawa",
    "party": "PPBM-Pakatan Harapan ",
    "spouse": "Siti Hasmah",
    "children": "7 (including Marina, Mokhzani and Mukhriz)",
    "alma_mater": "National University of Singapore",
    "DATE_TIME": "2018-05-16T21:16:22Z"
}