{
    "name": "Funimation Productions, LLC",
    "former_name": "FUNimation Productions (1994\u20132005) FUNimation Entertainment (2005\u20132011)",
    "area_served": "Worldwide",
    "key_people": "Gen Fukunaga (founder & chairman) Colin Decker (general manager)",
    "products": "Anime, motion pictures, Japanese/Asian cinema",
    "owner": "Sony (95%,,  Sony Pictures Entertainment and Sony Music Entertainment Japan joint ownership ) Gen Fukunaga (5%)",
    "divisions": "Funimation Films",
    "subsid": "AnimeLab, Madman Anime Group, Manga Entertainment  (UK branch only, US branch owned by Lionsgate Home Entertainment) , Wakanim",
    "DATE_TIME": "2020-02-09T12:50:11Z"
}