{
    "name": "Regent University",
    "religious_affiliation": "Interdenominational   Evangelical",
    "chancellor": "Pat Robertson",
    "students": "10,365",
    "undergrad": "4,408",
    "postgrad": "5,957",
    "other": "983 (non-degree seeking, first professional)",
    "faculty": "138 (Full-time) and 48 (Part-time)",
    "administrative_staff": "402",
    "athletics_affiliations": "NCCAA",
    "campus": "Suburban",
    "endowment": "$366,187,000",
    "DATE_TIME": "2023-01-21T02:42:17Z"
}