{
    "item1_style": [],
    "status": "Partially recognized state, UN observer state, Recognized by 137 UN member states",
    "largest_city": "Gaza City",
    "official_languages": "Arabic",
    "demonym": "Palestinian",
    "leader_title1": "President",
    "leader_name1": "Mahmoud Abbas b",
    "leader_title2": "Prime Minister",
    "leader_name2": "Mohammad Shtayyeh",
    "leader_title3": "Speaker of Parliament",
    "leader_name3": "Salim Zanoun",
    "sovereignty_type": "Formation",
    "established_event3": "Sovereignty dispute with Israel",
    "area_km2": "6,020",
    "area_rank": "163rd",
    "area_sq_mi": "2,320",
    "percent_water": "3.5",
    "area_label3": "Gaza Strip",
    "area_data3": "360 km",
    "population_estimate": "4,816,503",
    "population_estimate_year": "2016",
    "population_estimate_rank": "123rd",
    "population_density_km2": "731",
    "population_density_sq_mi": "1,895",
    "GDP_PPP": "$11.95 billion a",
    "GDP_PPP_year": "2008 a",
    "GDP_PPP_rank": "\u2013",
    "GDP_PPP_per_capita": "$2,900 a",
    "GDP_PPP_per_capita_rank": "\u2013",
    "Gini": "35.5",
    "Gini_year": "2009",
    "HDI": "0.677",
    "HDI_year": "2014",
    "HDI_change": "increase",
    "HDI_rank": "113th",
    "footnote_c": "The territories claimed are under Israeli occupation. ",
    "DATE_TIME": "2019-03-11T10:09:12Z"
}