{
    "common_name": "Algeria",
    "largest_city": "capital",
    "official_languages": [
        "Arabic",
        "Berber"
    ],
    "languages": "Algerian Arabic (Darja), ",
    "ethnic_groups": "1% others",
    "demonym": "Algerian",
    "leader_title1": "President",
    "leader_name1": "Abdelmadjid Tebboune",
    "leader_title2": "Prime Minister",
    "leader_name2": "Aymen Benabderrahmane",
    "leader_title3": "Council President",
    "leader_name3": "Salah Goudjil",
    "leader_title4": "Assembly President",
    "leader_name4": "Ibrahim Boughali",
    "sovereignty_type": "Formation",
    "established_event3": "Kingdom of Ouarsenis",
    "established_date3": "430 | established_event2     = Kingdom of Atlava | established_date2      = 477 | established_event3     = Ifranid Emirate of Agadir (Tlemcen)",
    "established_event4": "Rustamid dynasty",
    "established_date4": "776",
    "established_event5": "Sulaymanid dynasty",
    "established_date5": "786",
    "established_event6": "Zirid Dynasty",
    "established_date6": "972",
    "established_event7": "Hammadid Dynasty",
    "established_date7": "1014",
    "established_event8": "Zayyanid dynasty",
    "established_date8": "1235",
    "established_event10": "Emirate of Abdelkader",
    "established_date10": "1832",
    "established_event11": "French Algeria",
    "established_date11": "5 july 1830",
    "established_event12": "Modern Algeria",
    "established_date12": "1962",
    "area_km2": "2381741",
    "area_rank": "10th",
    "area_sq_mi": "919595",
    "percent_water": "1.1",
    "population_estimate": "44,700,000  title=D\u00e9mographie",
    "population_estimate_year": "2021",
    "population_estimate_rank": "32nd",
    "population_density_km2": "17.7",
    "population_density_sq_mi": "47",
    "population_density_rank": "168th",
    "GDP_PPP": "$581.189 billion",
    "GDP_PPP_year": "2022",
    "GDP_PPP_rank": "43rd",
    "GDP_PPP_per_capita": "$13,002",
    "GDP_PPP_per_capita_rank": "111th",
    "GDP_nominal": "$191.941 billion",
    "GDP_nominal_year": "2022",
    "GDP_nominal_rank": "58th",
    "GDP_nominal_per_capita": "$4,294",
    "GDP_nominal_per_capita_rank": "130th",
    "Gini": "27.6",
    "Gini_year": "2011",
    "HDI": "0.748",
    "HDI_year": "2019",
    "HDI_change": "increase",
    "HDI_rank": "91st",
    "DATE_TIME": "2022-06-25T22:15:46Z"
}