{
    "name": "Amazon.com, Inc.",
    "trading_name": "Amazon",
    "former_name": "Cadabra, Inc. (1994\u201395)",
    "ISIN": "US0231351067",
    "hq_location_city": "Seattle, Washington",
    "hq_location_country": "U.S.",
    "area_served": "Worldwide",
    "revenue": "177.86 billion",
    "revenue_year": "2017",
    "operating_income": "4.106 billion",
    "income_year": "2017",
    "net_income": "3.033 billion",
    "net_income_year": "2017",
    "assets": "131.31 billion",
    "assets_year": "2017",
    "equity": "27.709 billion",
    "equity_year": "2017",
    "num_employees_year": "2017",
    "DATE_TIME": "2018-07-26T15:54:11Z"
}