{
    "name": "Assata Shakur",
    "known_for": "Black radical; convicted of murder and named one of FBI's Most Wanted Terrorists",
    "alias": "Joanne Chesimard, JoAnne Deborah Byron",
    "weight": "convert",
    "allegiance": "Black Panther Party, Black Liberation Army",
    "charge": "murder, attempted murder, armed robbery, bank robbery, and kidnapping",
    "conviction": "1977",
    "conviction_penalty": "Life sentence",
    "conviction_status": "Escaped",
    "reward_amount": "$2,000,000",
    "capture_status": "Fugitive",
    "wanted_by": "FBI",
    "wanted_since": "1973",
    "time_at_large": "40 years",
    "escaped": "November 2, 1979",
    "occupation": "Activist",
    "residence": "Cuba",
    "DATE_TIME": "2014-03-03T16:47:22Z"
}