{
    "width": "Thimphu is the largest economic centre of Bhutan",
    "year": "2015",
    "organs": "SAFTA",
    "gdp rank": "168th (nominal) / 148th (PPP)",
    "gdp": "$5.871 billion (2014)",
    "growth": "6.4% (2014)",
    "per capita": "$7,700 (2014)",
    "sectors": "agriculture: 14.4%, industry: 41.6%, services: 44% (2014)fact",
    "date": "April 2016",
    "inflation": "9.6% (2014 est.)",
    "poverty": "12% (2012)",
    "gini": "38.7 (2012)",
    "edbr": "125<ref name",
    "publisher": "accessdate",
    "accessdate": "21 July 2015  |labour",
    "labour": "345,800 (2013)",
    "occupations": "agriculture: 56%, industry: 22%, services: 22% (2013)",
    "unemployment": "2.9% (2013)",
    "industries": "cement, wood products, processed fruits, alcoholic beverages, calcium carbide, tourism",
    "exports": "$650.3 million (2014) |export-goods",
    "imports": "$980.6 million (2014)",
    "debt": "$713.3 million (2006)",
    "revenue": "$407.1 million (2014)",
    "expenses": "$614 million (the government of India finances nearly one-quarter of Bhutan's budget expenditures) (2014)",
    "aid": "$90.02 million (India) (2005)",
    "cianame": "bt",
    "spelling": "US ",
    "DATE_TIME": "2016-07-26T21:07:38Z"
}