{
    "ground": "Oakwell",
    "capacity": "23,287<ref name",
    "clubname": "Barnsley",
    "owner": "Chien Lee Pacific Media Group (Paul Conway, Grace Hung, James Cryne, Neerav Parekh)",
    "chairman": "Chien Lee (co-chairman) Paul Conway (co-chairman)",
    "manager": "Poya Asbaghi",
    "league": "English football updater",
    "season": "English football updater",
    "position": "English football updater",
    "current": "2021\u201322 Barnsley F.C. season ",
    "DATE_TIME": "2022-02-25T17:28:45Z"
}