{
    "name": "Miami University",
    "academic_affiliations": [
        "GC3",
        "Space-grant"
    ],
    "endowment": "$558.4 million (2020)",
    "president": "Gregory Crawford",
    "provost": "Jason Osborne",
    "students": "19,752 (Oxford) 24,377 (all campuses) ",
    "undergrad": "17,327 (Oxford) 21,991 (all campuses)",
    "postgrad": "2,425 (Oxford)",
    "academic_staff": "973 (Oxford) 1,130 (all campuses)",
    "campus": "College Town, ",
    "DATE_TIME": "2022-04-09T19:17:15Z"
}