{"2011-05-29T09:39:19Z": {"WCL_division": "N/A"}, "2017-10-15T19:18:03Z": {"name": "Seychelles", "captain": "Kaushal Patel", "coach": "Ramesh Venkateshwarlu", "WCL_division": "Africa Division 2"}, "2021-10-12T15:00:17Z": {"name": "Seychelles", "captain": "Kaushal Patel", "coach": "Ramesh Venkateshwarlu", "num_t20is": "0", "num_t20is_this_year": "0", "t20i_record": "0 (0 ties, 0 no result)", "t20i_record_this_year": "0 (0 ties, 0 no result)"}, "2021-10-16T15:25:17Z": {"name": "Seychelles", "captain": "Kaushal Patel", "coach": "Ramesh Venkateshwarlu", "num_t20is": "1", "num_t20is_this_year": "1", "t20i_record": "0/1 (0 ties, 0 no result)", "t20i_record_this_year": "0/1 (0 ties, 0 no result)"}, "2021-10-17T10:12:36Z": {"name": "Seychelles", "captain": "Kaushal Patel", "coach": "Ramesh Venkateshwarlu", "num_t20is": "2", "num_t20is_this_year": "2", "t20i_record": "1/1 (0 ties, 0 no result)", "t20i_record_this_year": "1/1 (0 ties, 0 no result)"}, "2021-10-26T11:05:39Z": {"name": "Seychelles", "captain": "Kaushal Patel", "coach": "Ramesh Venkateshwarlu", "t20i_rank": "77th", "t20i_rank_best": "77th  (21-Oct-2021)", "num_t20is": "6", "num_t20is_this_year": "6", "t20i_record": "2/4 (0 ties, 0 no result)", "t20i_record_this_year": "2/4 (0 ties, 0 no result)"}, "2022-11-17T10:37:55Z": {"name": "Seychelles", "captain": "Krishna", "coach": "Aruna Hathurusinghe", "t20i_rank": "69th", "t20i_rank_best": "65th (2-May-2022)", "num_t20is": "6", "num_t20is_this_year": "0", "t20i_record": "2/4 (0 ties, 0 no result)", "t20i_record_this_year": "0/0 (0 ties, 0 no result)"}}