{
    "gdp": "$306,663 million http://research.stlouisfed.org/fred2/graph/?id",
    "year": "2016",
    "per capita": "$48,730  http://research.stlouisfed.org/fred2/graph/?id",
    "poverty": "13.7%",
    "gini": "0.453 http://factfinder.census.gov/servlet/DTTable?_bm",
    "labor": "2,819,800",
    "unemployment": "3.0%   | average gross salary",
    "gross median": "| average net salary",
    "revenue": "$8,586.401 million",
    "expenses": "$7,722 million http://nasbo.org/LinkClick.aspx?fileticket",
    "usebelowbox": "yes | presentUS$asdefault",
    "DATE_TIME": "2016-04-05T16:36:00Z"
}