{
    "name": "Amitabh Bachchan",
    "education": "B.Sc (1962)",
    "occupation": [
        "Actor",
        "producer",
        "singer",
        "television presenter"
    ],
    "organization": "Amitabh Bachchan Corporation",
    "works": "Full list",
    "children": [
        "Abhishek Bachchan",
        "Shweta Bachchan Nanda"
    ],
    "awards": "Full List",
    "honours": "Dadasaheb Phalke Award (2019)  Padma Vibhushan (2015) Legion of Honour (2007) Padma Bhushan (2001) Padma Shri (1984)",
    "DATE_TIME": "2022-09-13T07:59:21Z"
}