{
    "name": "Sun Conference",
    "logo_size": "200",
    "association": "National Association of Intercollegiate Athletics",
    "teams": "10 (9 in 2023)",
    "sports": "17",
    "mens": "9",
    "womens": "8",
    "region": "Southern United States",
    "formerly": "Florida Intercollegiate Athletic Conference (1990\u20131992) Florida Sun Conference (1992\u20132008)",
    "headquarters": "Daytona Beach, Florida",
    "commissioner": "Dustin Wilke",
    "map": "FSC-USA-states.PNG",
    "map_size": "250 ",
    "DATE_TIME": "2023-03-02T01:53:02Z"
}