{
    "name": "Nova Southeastern University",
    "endowment": "$174.2 million (2020)",
    "budget": "$590 million (2019)",
    "chancellor": "Ray F. Ferrero Jr. ",
    "president": "George L. Hanbury II",
    "provost": "Ralph V. Rogers",
    "academic_staff": "1,676",
    "students": "20,576 ",
    "undergrad": "5,666",
    "postgrad": "14,910",
    "campus": "Suburban, ",
    "former_names": "Nova University of Advanced Technology (1964-74)  Nova University (1974-94)  Southeastern College of Osteopathic Medicine (1981-86)  Southeastern University of the Health Sciences (1986-94) ",
    "academic_affiliations": [
        "ICUF",
        "NAICU",
        "SFEC",
        ""
    ],
    "DATE_TIME": "2021-08-22T20:08:01Z"
}