{
    "name": "Danish Sarwar  |honorific-suffix   =  |image              = Sarwar Danish in 2011-cropped.jpg |imagesize          = |alt                =  |caption            = |office             =Vice President of Afghanistan |term_start         = 29 September 2014 |term_end           =  |president          =Ashraf Ghani |predecessor        = Yunus Qanuni |successor          = |blank2             =  |data2              =  |blank3             =  |data3              =  |blank4             =  |data4              =  |blank5             =  |data5              =   |nickname           =  |allegiance         =  |branch             =  |serviceyears       =  |rank               =  |unit               =  |commands           =  |battles            =  |awards             =  |military_blank1    =  |military_data1     =  |military_blank2    =  |military_data2     =  |military_blank3    =  |military_data3     =  |military_blank4    =  |military_data4     =  |military_blank5    =  |military_data5     =  |honorific_prefix  =General",
    "office": "Vice President of Afghanistan",
    "term_start": "29 September 2014",
    "president": "Ashraf Ghani",
    "rank": "|unit               =  |commands           =  |battles            =  |awards             =  |military_blank1    =  |military_data1     =  |military_blank2    =  |military_data2     =  |military_blank3    =  |military_data3     =  |military_blank4    =  |military_data4     =  |military_blank5    =  |military_data5     =  |honorific_prefix  =General |name              =Abdul Rashid Dostum |honorific_suffix  = |native_name       =  \u0639\u0628\u062f\u0627\u0644\u0631\u0634\u06cc\u062f \u062f\u0648\u0633\u062a\u0645 |native_name_lang  = |image         = Abdul Rashid Dostum VOA Jan 22 2002 retouched.jpg |image_size    =  |caption       = Abdul Rashid Dostum in 2002 |birth_date    = death_date    =  |birth_place   =Jowzjan, Afghanistan |nationality   =Afghan |ethnicity     =Uzbek |death_place   =  |placeofburial = |placeofburial_label = |placeofburial_coordinates =  |nickname      = |birth_name    = |allegiance    =",
    "battles": "|awards             =  |military_blank1    =  |military_data1     =  |military_blank2    =  |military_data2     =  |military_blank3    =  |military_data3     =  |military_blank4    =  |military_data4     =  |military_blank5    =  |military_data5     =  |honorific_prefix  =General |name              =Abdul Rashid Dostum |honorific_suffix  = |native_name       =  \u0639\u0628\u062f\u0627\u0644\u0631\u0634\u06cc\u062f \u062f\u0648\u0633\u062a\u0645 |native_name_lang  = |image         = Abdul Rashid Dostum VOA Jan 22 2002 retouched.jpg |image_size    =  |caption       = Abdul Rashid Dostum in 2002 |birth_date    = death_date    =  |birth_place   =Jowzjan, Afghanistan |nationality   =Afghan |ethnicity     =Uzbek |death_place   =  |placeofburial = |placeofburial_label = |placeofburial_coordinates =  |nickname      = |birth_name    = |allegiance    =",
    "awards": "|military_blank1    =  |military_data1     =  |military_blank2    =  |military_data2     =  |military_blank3    =  |military_data3     =  |military_blank4    =  |military_data4     =  |military_blank5    =  |military_data5     =  |honorific_prefix  =General |name              =Abdul Rashid Dostum |honorific_suffix  = |native_name       =  \u0639\u0628\u062f\u0627\u0644\u0631\u0634\u06cc\u062f \u062f\u0648\u0633\u062a\u0645 |native_name_lang  = |image         = Abdul Rashid Dostum VOA Jan 22 2002 retouched.jpg |image_size    =  |caption       = Abdul Rashid Dostum in 2002 |birth_date    = death_date    =  |birth_place   =Jowzjan, Afghanistan |nationality   =Afghan |ethnicity     =Uzbek |death_place   =  |placeofburial = |placeofburial_label = |placeofburial_coordinates =  |nickname      = |birth_name    = |allegiance    =",
    "ethnicity": "Uzbek",
    "DATE_TIME": "2014-09-29T08:17:59Z"
}