{
    "Name": "Ringo Starr",
    "Img": "ringo.jpg",
    "Img_capt": "Ringo Starr in 2007",
    "Landscape": "Yes",
    "Background": "solo_singer",
    "Birth_name": "Richard Starkey",
    "Alias": "Ringo",
    "Born": "Birth date and age",
    "Origin": "Liverpool, England",
    "Instrument": "drum kit",
    "Genre": "Rock music",
    "Occupation": "Musician, songwriter, actor",
    "Years_active": "1957 \u2013 present",
    "Label": "Parlophone Records",
    "Associated_acts": "The Beatles, Rory Storm and the Hurricanes, Ringo Starr All-Starr Band",
    "URL": "http://www.ringostarr.com/ ringostarr.com",
    "Notable_instruments": "Ludwing Drumset ",
    "DATE_TIME": "2008-06-06T00:03:50Z"
}