{
    "name": "Fudan University",
    "image_name": "Fudan University.png",
    "former_names": "Fudan Public School (1905) ,  Fudan College ,  Private Fudan University (1917-1941) National Fudan University (1941-1949)",
    "president": "Xu Ningsheng",
    "head": "vice-president",
    "faculty": "2,700",
    "staff": "5,800",
    "students": "31,900",
    "undergrad": "14,100",
    "postgrad": "14,800 (includi",
    "doctoral": "tudents)",
    "other": "3,000 (exchange students)",
    "campus": "604 acres Urban: Handan campus Fenglin campus Jiangw",
    "affiliations": "C9, Universitas 21, AEARU, APRU, BRICS Universities League, Council on Business & Society, Washington University in St. Louis McDonnell International Scholars Academy",
    "DATE_TIME": "2019-08-05T14:43:09Z"
}