{
    "common_name": "Marshall Islands",
    "official_languages": "English, Marshallese",
    "demonym": "Marshallese",
    "ethnic_groups_year": "2006",
    "latd": "7 |latm=7 |latNS=N |longd=171 |longm=4 |longEW=E",
    "largest_city": "capital",
    "leader_title1": "President",
    "leader_name1": "Christopher Loeak",
    "area_rank": "213th",
    "area_magnitude": "1 E7",
    "area_km2": "181",
    "area_sq_mi": "70",
    "percent_water": "n/a ( negligible )",
    "population_estimate": "68,000",
    "population_estimate_rank": "205th",
    "population_estimate_year": "2009",
    "population_census": "56,429",
    "population_census_year": "2003",
    "population_density_km2": "342.5",
    "population_density_sq_mi": "885.7",
    "population_density_rank": "28th",
    "GDP_PPP": "$115 million",
    "GDP_PPP_rank": "220th",
    "GDP_PPP_year": "2001",
    "GDP_PPP_per_capita": "$2,900 a",
    "GDP_PPP_per_capita_rank": "195th",
    "sovereignty_type": "Independence",
    "HDI": "n/a",
    "HDI_category": "unranked",
    "country_code": "MHL",
    "DATE_TIME": "2012-11-03T01:30:51Z"
}