{
    "name": "Michael Collins",
    "type": "File:Michael Collins Signature.svg",
    "status": "Retired",
    "alma_mater": "United States Military Academy",
    "occupation": "Test pilot",
    "rank": "Brigadier General, United States Air Force",
    "selection": "List of astronauts by selection#1963",
    "eva1": "2",
    "eva2": "1 hour 28 minutes",
    "time": "11 days, 2 hours, 04 minutes, 43 seconds",
    "mission": "Gemini 10, Apollo 11",
    "insignia": "File:Ge10Patch orig.png",
    "awards": "|link",
    "DATE_TIME": "2014-12-18T15:00:53Z"
}