{
    "name": "Ajit Jogi",
    "residence": "Raipur",
    "office1": "President, Janta Congress Chhattisgarh",
    "term_start1": "2016",
    "predecessor1": "Post Created",
    "office2": "1st Chief Minister of Chhattisgarh",
    "term2": "9 November 2000 \u2013 6 December 2003",
    "predecessor2": "Post Created",
    "successor2": "Raman Singh",
    "office3": "Member of Chhattisgarh Legislative Assembly for Marwahi",
    "term_start3": "11 December 2018",
    "predecessor3": "Amit Jogi",
    "term_start4": "2001",
    "term_end4": "2013",
    "predecessor4": "Ram Dayal Uike",
    "successor4": "Amit Jogi",
    "office5": "Member of Indian Parliament",
    "constituency5": "Mahasamund",
    "term_start5": "2004",
    "term_end5": "2008",
    "predecessor5": "Shyama Charan Shukla",
    "successor5": "Chandulal Sahu",
    "constituency6": "Raigarh",
    "term_start6": "1998",
    "term_end6": "1999",
    "predecessor6": "Nand Kumar Sai",
    "successor6": "Vishnudeo Sai",
    "office7": "MP of Rajya Sabha for Madhya Pradesh",
    "term_start7": "1986",
    "term_end7": "1998",
    "party": "Chhattisgarh Janata Congress",
    "otherparty": "Indian National Congress ",
    "spouse": "Dr. Renu Jogi",
    "children": "Amit Jogi",
    "DATE_TIME": "2020-01-08T18:27:40Z"
}