{
    "name": "Berklee College of Music",
    "president": "Erica Muhl",
    "faculty": "522 ",
    "endowment": "$338.8 million (2020)",
    "students": "6,000 http://colleges.usnews.rankingsandreviews.com/best-colleges/berklee-college-2126 \"Berklee College of Music\", US New & world Reports Education Rankings 2016 Colleges.usnews.rankingsandreviews.com, Access May 12, 2017",
    "campus": "Urban",
    "academic_affiliations": "Professional Arts Consortium",
    "DATE_TIME": "2021-09-25T04:15:47Z"
}