{
    "name": "Kansas State University",
    "former_names": "Kansas State Agricultural College (1863\u20131931), Kansas State College of Agriculture and Applied Science (1931\u20131959)",
    "academic_affiliations": [
        "ASAIHL",
        "URA",
        "Space-grant"
    ],
    "endowment": "$912 million (2022)",
    "president": "Richard Linton",
    "provost": "Charles Taber",
    "academic_staff": "1,404",
    "students": "19,722 (Fall 2022) ",
    "undergrad": "15,046 (Fall 2022)",
    "campus": "Small City,   ",
    "athletics_nickname": "Wildcats",
    "free_label1": "Other campuses",
    "free1": [
        "Salina",
        "Olathe"
    ],
    "free_label2": "Newspaper",
    "free2": "''Kansas State Collegian'' ",
    "DATE_TIME": "2023-03-28T02:30:06Z"
}