{
    "region": "Western Philosophy",
    "color": "#B0C4DE",
    "image_name": "Hilary Putnam.jpg",
    "name": "Hilary Whitehall Putnam",
    "school_tradition": "Analytic philosophy",
    "main_interests": "Philosophy of mind, Philosophy of language, Philosophy of mathematics, Metaphilosophy, Epistemology",
    "notable_ideas": "Multiple realizability, Functionalism (philosophy of mind)",
    "influences": "Willard Van Orman Quine",
    "influenced": "Jerry Fodor, Ned Block, Joseph LeDoux, Tyler Burge, David Marr, Daniel Dennett, David Lewis, Donald Davidson ",
    "DATE_TIME": "2011-01-03T15:19:39Z"
}