{
    "name": "Jane Wyman",
    "birthname": "Sarah Jane Mayfield",
    "birthdate": "birth date",
    "birthplace": "flagicon",
    "deathdate": "death date and age",
    "deathplace": "flagicon",
    "occupation": "actor",
    "yearsactive": "1932-1993",
    "spouse": "Ernest Eugene Wyman (m.1933), Myron Futterman (1937-1938), Ronald Reagan (1940-1948), Fred Karger (1952-1954), Fred Karger (1961-1965)",
    "children": "Maureen Reagan (1941-2001) ,  Michael Reagan (born in 1945)",
    "academyawards": "'''Academy Award for Best Actress",
    "goldenglobeawards": "'''Best Actress - Motion Picture Drama''', 1949 ''Johnny Belinda'', 1952 ''The Blue Veil'' ,  '''Best Actress - Drama Series''', 1983 ''Falcon Crest'' ",
    "DATE_TIME": "2007-09-23T00:38:16Z"
}