{
    "name": "Southeastern Conference",
    "short_name": "SEC",
    "established": "1933",
    "logo_size": "150",
    "association": "NCAA",
    "division": "Division I",
    "subdivision": "FBS",
    "members": "12",
    "sports": "17",
    "mens": "8",
    "womens": "9",
    "region": "Southern United States",
    "hq_city": "Birmingham",
    "hq_stateabb": "AL",
    "hq_state": "Alabama",
    "commissioner": "Michael Slive",
    "since": "2002",
    "champion": "LSU Tigers",
    "color": "161149",
    "font_color": "FFCB39",
    "map": "SEC-USA-states.PNG",
    "map_size": "275 ",
    "DATE_TIME": "2010-01-01T02:55:54Z"
}