{
    "Name": "Daniel Johns",
    "Img": "Daniel Johns Big Day Out 08.jpg",
    "Img_capt": "Daniel Johns performing at the Big Day Out in 2008.",
    "Background": "solo_singer",
    "Birth_name": "Daniel Paul Johns",
    "Alias": "Young Modern",
    "Born": "birth date and age",
    "Instrument": "Guitar, Piano",
    "Genre": "Grunge music",
    "Occupation": "Musician, Songwriter",
    "Years_active": "1992-present",
    "Label": "Epic Records",
    "Associated_acts": "Silverchair, The Dissociatives",
    "URL": "http://www.chairpage.com",
    "Notable_instruments": "Fender Telecaster, Rickenbacker  ",
    "DATE_TIME": "2008-07-11T13:05:02Z"
}