{
    "Name": "Billy Joel",
    "Img": "File:Billy Joel Shankbone NYC 2009.jpg",
    "Img_capt": "Joel at the 2009 premiere of the Metropolitan Opera",
    "Background": "solo_singer",
    "Birth_name": "William Martin Joel<ref name",
    "Alias": "Bill Martin Erlewine, Stephen Thomas (2006). \"http://www.allmusic.com/cg/amg.dll?p",
    "Born": "birth date and age",
    "Origin": "Bronx, New York, United States",
    "Instrument": "singing",
    "Genre": "Pop music",
    "Occupation": "Singer-songwriter, musician",
    "Years_active": "1964\u2013present",
    "Label": "Columbia Records",
    "Associated_acts": "Echoes (band)",
    "URL": "http://www.billyjoel.com/ BillyJoel.com",
    "DATE_TIME": "2009-09-22T03:46:07Z"
}