{
    "name": "Joseph Kabila",
    "office": "President of the Democratic Republic of the Congo",
    "order": "4th",
    "primeminister": "Antoine Gizenga, Adolphe Muzito, Louis Alphonse Koyagialo ",
    "vicepresident": "Azarias Ruberwa, Arthur Z'ahidi Ngoma, Abdoulaye Yerodia Ndombasi, Jean-Pierre Bemba ",
    "term_start": "26 January 2001, ",
    "party": "People's Party for Reconstruction and Democracy",
    "spouse": "Olive Lembe di Sita",
    "alma_mater": "Makerere University, People's Liberation Army National Defense University",
    "rank": "Major-general",
    "allegiance": "Democratic Republic of the Congo",
    "branch": "Armed Forces of the Democratic Republic of the Congo ",
    "DATE_TIME": "2019-01-10T02:57:52Z"
}