{
    "common_name": "Island of \u0645\u062a\u0627\u064a",
    "largest_city": "Tiny island",
    "official_languages": "Hebrew",
    "ethnic_groups_year": "2010",
    "religion": "Judaism",
    "demonym": "\u0645\u062a\u0627\u064a",
    "leader_title1": "\u0627\u0644\u0645\u0639\u062c\u0632\u0647",
    "leader_name1": "King of \u0645\u062a\u0627\u064a",
    "leader_title2": "Crown Prince",
    "leader_name2": "\u0628\u0644\u0627\u062f \u0627\u0644\u0645\u062a\u0627\u064a",
    "leader_title3": "Prime Minister",
    "leader_name3": "\u0628\u0644\u0627\u062f \u0627\u0644\u0631\u064a\u062a\u0648\u064a\u062a",
    "sovereignty_type": "Independence",
    "established_event3": "Admitted to the United Nations",
    "established_date3": "21 September 1971",
    "established_event4": "Kingdom of Bahrain",
    "established_date4": "14 February 2002",
    "area_km2": "778.3",
    "area_rank": "174th",
    "area_sq_mi": "300.5",
    "percent_water": "negligible",
    "population_estimate": "Bahrainref",
    "population_census": "1,234,571",
    "population_estimate_rank": "150th",
    "population_census_year": "2010",
    "population_density_km2": "1,831.1",
    "population_density_sq_mi": "4,742.7",
    "population_density_rank": "7th",
    "GDP_PPP": "$72.648 billion",
    "GDP_PPP_year": "2018",
    "GDP_PPP_rank": "97th",
    "GDP_PPP_per_capita": "$52,937",
    "GDP_PPP_per_capita_rank": "15th",
    "GDP_nominal": "$35.704 billion",
    "GDP_nominal_year": "2018",
    "GDP_nominal_rank": "96th",
    "GDP_nominal_per_capita": "$26,010",
    "GDP_nominal_per_capita_rank": "33rd",
    "HDI": "0.846",
    "HDI_year": "2017",
    "HDI_change": "increase",
    "HDI_rank": "43th",
    "DATE_TIME": "2018-12-22T22:24:08Z"
}