{
    "president": "Dr. MYRNA Q. MALLARI",
    "postgrad_label": "graduate",
    "faculty": "356",
    "staff": "179 administrative personnel, 355 staff",
    "students": "12,562",
    "head": "Hon. RUPERTO SANGALANG , Chairman, CHED",
    "postgrad": "MA.ED, MAN, MBA, MPA, MSIT",
    "doctoral": "Ed.D, DPA, DBA",
    "affiliations": "Accrediting Agency of Chartered Colleges and Universities in the Philippines,, Asia-Pacific Qualifying Network,, Association of Universities of Asia and the Pacific,, Asia University Federation,,                     International Association of Universities",
    "DATE_TIME": "2015-01-02T16:45:56Z"
}