{
    "name": "Coventry University",
    "endowment": "\u00a328 million (2015) ",
    "budget": "\u00a3787.5 million ",
    "chancellor": "Margaret Casely-Hayford",
    "vice_chancellor": "John Latham ",
    "campus": "Urban, CU London",
    "former_names": "Coventry Polytechnic (1987\u20131992), Lanchester Polytechnic (1970\u20131987)",
    "colours": "Coventry Blue",
    "image_name": "File:Shield_of_the_Coventry_University.svg",
    "faculty": "1,890",
    "DATE_TIME": "2022-07-16T12:30:49Z"
}