{
    "Name": "Shad Moss",
    "Img_capt": "Bow Wow",
    "Background": "solo_singer",
    "Birthname": "Shad Gregory Moss",
    "Nicknames": "Bow Wow, Lil' Bow Wow & Lamborghini Moss",
    "Born": "birth date and age",
    "Origin": "Columbus, Ohio, United States",
    "Genre": "Hip hop (music)",
    "Occupation": "Rapper, actor, and philantropist",
    "Instrument": "Keyboards",
    "Years_active": "1993\u2014present",
    "Label": "So So Def Recordings",
    "Associated_acts": "Jagged Edge, Jermaine Dupri, Lil Wayne, Omarion, Snoop Dogg",
    "URL": "http://www.myspace.com/bowwow myspace.com/bowwow",
    "DATE_TIME": "2009-08-19T01:16:31Z"
}