{
    "name": "Peshawar Zalmi lang",
    "captain": "Wahab Riaz",
    "coach": "Daren Sammy",
    "city": "Peshawar, Khyber Pakhtunkhwa, Pakistan",
    "colors": "File:Peshawar Zalmi team",
    "owner": "Javed Afridi (Haier Pakistan)<ref name",
    "founded": "Start date and age",
    "ground": "Arbab Niaz Stadium",
    "capacity": "35,000 (after reconstruction)",
    "h_pattern_la": "_blackborder",
    "h_pattern_b": "_black_chest",
    "h_pattern_ra": "_blackborder",
    "h_leftarm": "FFFF00",
    "h_body": "FFFF00",
    "h_rightarm": "FFFF00",
    "h_pants": "FFFF00",
    "h_title": "Home kit",
    "a_pattern_la": "_borderonblack",
    "a_pattern_b": "_thinsidesonblack",
    "a_pattern_ra": "_borderonblack",
    "a_leftarm": "C5B358",
    "a_body": "C5B358",
    "a_rightarm": "C5B358",
    "a_pants": "000000",
    "a_title": "Alternate kit",
    "DATE_TIME": "2021-03-07T16:16:13Z"
}