{
    "name": "Loughborough University",
    "image_name": "File:Crest Shield of Loughborough University 1v.svg",
    "endowment": "\u00a32.1 million ",
    "budget": "\u00a3300.8 million ",
    "chancellor": "The Lord Coe",
    "vice_chancellor": "Robert Allison",
    "head": "Paul Michell",
    "students": "18,439 (2018/2019)",
    "other": "1,205 FE ",
    "campus": "Suburban, single-si",
    "affiliations": "Universities UK, Wallace Group, AMBA, EUA, ACU, EMUA, EQUIS, ESRC, SEFI, M5 Universities, UNITECH ",
    "DATE_TIME": "2020-10-02T13:57:52Z"
}