{
    "Name": "Bob Geldof",
    "Img": "Bob Geldof Rock am Ring 1987.jpg",
    "Img_capt": "Geldof in 1987",
    "Background": "solo singer",
    "Birth_name": "Robert Frederick Zenon Geldof",
    "Born": "birth date and age",
    "Instrument": "Lead singer",
    "Genre": "Rock music",
    "Occupation": "Musician, singer-songwriter, activism",
    "Years_active": "1975&ndash;present",
    "Associated_acts": "Boomtown Rats",
    "URL": "http://www.bobgeldof.com/ www.bobgeldof.com",
    "DATE_TIME": "2009-10-08T20:56:46Z"
}