{
    "common_name": "Holy Roman Empire",
    "continent": "Europe",
    "region": "Central Europe",
    "status": "Empire",
    "life_span": "962\u20131806",
    "border_p3": "no",
    "religion": "Roman Catholicism (962\u20131806), Evangelical Lutheranism (1555\u20131806), Calvinism (Reformed) (1648\u20131806), , ''see details''",
    "leader1": "Otto I  (first)",
    "leader2": "Francis II  (last)",
    "year_leader1": "800\u2013814",
    "year_leader2": "962\u2013973",
    "year_leader3": "1792\u20131806",
    "title_leader": "Emperor ",
    "DATE_TIME": "2018-09-28T17:23:43Z"
}